ssbh_data_py-0.9.1.dist-info/METADATA
ssbh_data_py-0.9.1.dist-info/WHEEL
ssbh_data_py/__init__.py
ssbh_data_py/__init__.pyi
ssbh_data_py/adj_data.pyi
ssbh_data_py/anim_data.pyi
ssbh_data_py/hlpb_data.pyi
ssbh_data_py/matl_data.pyi
ssbh_data_py/mesh_data.pyi
ssbh_data_py/meshex_data.pyi
ssbh_data_py/modl_data.pyi
ssbh_data_py/skel_data.pyi
ssbh_data_py/ssbh_data_py.cpython-312-darwin.so
ssbh_data_py-0.9.1.dist-info/RECORD
