Metadata-Version: 2.4
Name: ssbh_data_py
Version: 0.9.1
Author: ScanMountGoat
